cp_based_fair_maker/__init__.py
cp_based_fair_maker/algorithms/__init__.py
cp_based_fair_maker/algorithms/cp_transformer.py
cp_based_fair_maker/algorithms/cp_undersampler.py
cp_based_fair_maker/algorithms/models/__init__.py
cp_based_fair_maker/algorithms/models/fair_score_cp_transformable.py
cp_based_fair_maker/datasets/__init__.py
cp_based_fair_maker/datasets/binary_label_dataset.py
cp_based_fair_maker/datasets/dataset.py
cp_based_fair_maker/datasets/multiclass_label_dataset.py
cp_based_fair_maker/datasets/raw_dataset.py
cp_based_fair_maker/datasets/regression_dataset.py
cp_based_fair_maker/errors/__init__.py
cp_based_fair_maker/errors/errors.py
cp_based_fair_maker/examples/__init__.py
cp_based_fair_maker/metrics/__init__.py
cp_based_fair_maker/metrics/class_imbalance.py
cp_based_fair_maker/metrics/constants.py
cp_based_fair_maker/metrics/dataset_metric.py
cp_based_fair_maker/metrics/fair_score.py
cp_based_fair_maker/metrics/raw_metric.py
cp_based_fair_maker/utils/__init__.py
cp_based_fair_maker/utils/dataframe.py
cp_based_fair_maker/utils/operations.py
cp_based_fair_maker/utils/range.py
cp_based_fair_maker-0.0.4.dist-info/licenses/LICENSE
cp_based_fair_maker-0.0.4.dist-info/METADATA
cp_based_fair_maker-0.0.4.dist-info/WHEEL
cp_based_fair_maker-0.0.4.dist-info/top_level.txt
cp_based_fair_maker-0.0.4.dist-info/RECORD
