Metadata-Version: 2.4
Name: cp_based_fair_maker
Version: 0.0.4
Summary: A library that provides metrics and algorithms for bias assessment in datasets using CP-based methods
Author-email: Eden Houndonougbo <eden.houndonougbo@friare.org>
License-Expression: BSD-3-Clause
Project-URL: Homepage, https://github.com/fedenh/cp-based-fair-maker
Project-URL: Issues, https://github.com/fedenh/cp-based-fair-maker/issues
Keywords: AI,fairness,datasets,CP,undersampling,oversampling
Classifier: Programming Language :: Python :: 3
Classifier: Operating System :: OS Independent
Requires-Python: >=3.8
License-File: LICENSE
Requires-Dist: pandas
Requires-Dist: numpy
Requires-Dist: ortools
Requires-Dist: python-dateutil
Provides-Extra: dev
Requires-Dist: pytest; extra == "dev"
Requires-Dist: black; extra == "dev"
Requires-Dist: isort; extra == "dev"
Requires-Dist: mypy; extra == "dev"
Provides-Extra: docs
Requires-Dist: sphinx; extra == "docs"
Requires-Dist: sphinx-rtd-theme; extra == "docs"
Requires-Dist: alabaster; extra == "docs"
Requires-Dist: docutils; extra == "docs"
Requires-Dist: Pygments; extra == "docs"
Requires-Dist: babel; extra == "docs"
Requires-Dist: imagesize; extra == "docs"
Requires-Dist: snowballstemmer; extra == "docs"
Requires-Dist: sphinxcontrib-applehelp; extra == "docs"
Requires-Dist: sphinxcontrib-devhelp; extra == "docs"
Requires-Dist: sphinxcontrib-htmlhelp; extra == "docs"
Requires-Dist: sphinxcontrib-jsmath; extra == "docs"
Requires-Dist: sphinxcontrib-qthelp; extra == "docs"
Requires-Dist: sphinxcontrib-serializinghtml; extra == "docs"
Provides-Extra: excel
Requires-Dist: openpyxl; extra == "excel"
Requires-Dist: xlrd; extra == "excel"
Requires-Dist: XlsxWriter; extra == "excel"
Requires-Dist: python-calamine; extra == "excel"
Requires-Dist: pyxlsb; extra == "excel"
Dynamic: license-file
